crashlens/__init__.py
crashlens/__main__.py
crashlens/cli.py
crashlens/config/crashlens-policy.yaml
crashlens/config/pricing.yaml
crashlens/detectors/__init__.py
crashlens/detectors/detectors.md
crashlens/detectors/fallback_failure.py
crashlens/detectors/fallback_storm.py
crashlens/detectors/overkill_model_detector.py
crashlens/detectors/retry_loops.py
crashlens/parsers/__init__.py
crashlens/parsers/langfuse.py
crashlens/reporters/__init__.py
crashlens/reporters/markdown_formatter.py
crashlens/reporters/slack_formatter.py
crashlens/reporters/summary_formatter.py
crashlens/utils/__init__.py
crashlens/utils/pii_scrubber.py
crashlens_detector-1.5.0.dist-info/entry_points.txt
crashlens_detector-1.5.0.dist-info/LICENSE
crashlens_detector-1.5.0.dist-info/METADATA
crashlens_detector-1.5.0.dist-info/WHEEL
crashlens_detector-1.5.0.dist-info/RECORD
