Metadata-Version: 2.1
Name: crashlens-detector
Version: 1.5.0
Summary: CLI to detect GPT token waste from Langfuse logs
License: MIT
Author: Aditya Singh
Author-email: coding103856@gmail.com
Requires-Python: >=3.12,<4.0
Classifier: License :: OSI Approved :: MIT License
Classifier: Programming Language :: Python :: 3
Classifier: Programming Language :: Python :: 3.12
Requires-Dist: click (>=8.2.1,<9.0.0)
Requires-Dist: jinja2 (>=3.1.6,<4.0.0)
Requires-Dist: orjson (>=3.10.18,<4.0.0)
Requires-Dist: pyperclip (>=1.8.2,<2.0.0)
Requires-Dist: pyyaml (>=6.0.2,<7.0.0)
Requires-Dist: rich (>=14.0.0,<15.0.0)
